[
  {
    "id": "id_suffix_an",
    "root": "-an",
    "type": "suffix",
    "languageOrigin": "Indonesian",
    "meaning": "nominalizer; result/state",
    "examples": [
      {
        "word": "makanan",
        "meaning": "food",
        "sentence": "Makanan ini enak."
      },
      {
        "word": "minuman",
        "meaning": "drink",
        "sentence": "Minuman itu dingin."
      },
      {
        "word": "bacaan",
        "meaning": "reading material",
        "sentence": "Bacaan ini sulit."
      }
    ],
    "relatedRootIds": ["id_base_makan", "id_base_minum", "id_base_baca"],
    "pronunciationIpa": "/an/",
    "pronunciationVariants": [
      {
        "accent": "indonesian",
        "ipa": "an"
      }
    ]
  },
  {
    "id": "id_suffix_kan",
    "root": "-kan",
    "type": "suffix",
    "languageOrigin": "Indonesian",
    "meaning": "causative; benefactive",
    "examples": [
      {
        "word": "buatkan",
        "meaning": "make for someone",
        "sentence": "Buatkan saya kopi."
      },
      {
        "word": "carikan",
        "meaning": "find for someone",
        "sentence": "Carikan saya kunci itu."
      },
      {
        "word": "kirimkan",
        "meaning": "send for someone",
        "sentence": "Kirimkan surat ini."
      }
    ],
    "relatedRootIds": ["id_base_buat", "id_base_cari", "id_base_kirim"],
    "pronunciationIpa": "/kan/",
    "pronunciationVariants": [
      {
        "accent": "indonesian",
        "ipa": "kan"
      }
    ]
  },
  {
    "id": "id_suffix_i",
    "root": "-i",
    "type": "suffix",
    "languageOrigin": "Indonesian",
    "meaning": "locative; repetitive; directed at",
    "examples": [
      {
        "word": "tulisi",
        "meaning": "write on",
        "sentence": "Tulisi nama di kertas ini."
      },
      {
        "word": "kirimi",
        "meaning": "send to",
        "sentence": "Kirimi dia kabar baik."
      },
      {
        "word": "bawahi",
        "meaning": "supervise",
        "sentence": "Bawahi anak-anak itu."
      }
    ],
    "relatedRootIds": ["id_base_tulis", "id_base_kirim", "id_base_bawa"],
    "pronunciationIpa": "/i/",
    "pronunciationVariants": [
      {
        "accent": "indonesian",
        "ipa": "i"
      }
    ]
  },
  {
    "id": "id_suffix_nya",
    "root": "-nya",
    "type": "suffix",
    "languageOrigin": "Indonesian",
    "meaning": "definite; possessive; nominalizer",
    "examples": [
      {
        "word": "bacanya",
        "meaning": "his/her reading",
        "sentence": "Saya suka bacanya."
      },
      {
        "word": "tulisannya",
        "meaning": "his/her writing",
        "sentence": "Tulisannya bagus."
      },
      {
        "word": "makanannya",
        "meaning": "his/her food",
        "sentence": "Makanannya enak."
      }
    ],
    "relatedRootIds": ["id_suffix_an"],
    "pronunciationIpa": "/ɲa/",
    "pronunciationVariants": [
      {
        "accent": "indonesian",
        "ipa": "nya"
      }
    ]
  },
  {
    "id": "id_suffix_ku",
    "root": "-ku",
    "type": "suffix",
    "languageOrigin": "Indonesian",
    "meaning": "my",
    "examples": [
      {
        "word": "bacaku",
        "meaning": "my reading",
        "sentence": "Ini bacaku."
      },
      {
        "word": "tulisanku",
        "meaning": "my writing",
        "sentence": "Tulisanku masih berantakan."
      },
      {
        "word": "makananku",
        "meaning": "my food",
        "sentence": "Makananku hangat."
      }
    ],
    "relatedRootIds": ["id_suffix_nya"],
    "pronunciationIpa": "/ku/",
    "pronunciationVariants": [
      {
        "accent": "indonesian",
        "ipa": "ku"
      }
    ]
  },
  {
    "id": "id_suffix_mu",
    "root": "-mu",
    "type": "suffix",
    "languageOrigin": "Indonesian",
    "meaning": "your",
    "examples": [
      {
        "word": "bacamu",
        "meaning": "your reading",
        "sentence": "Itu bacamu."
      },
      {
        "word": "tulisanmu",
        "meaning": "your writing",
        "sentence": "Tulisanmu rapi."
      },
      {
        "word": "makananmu",
        "meaning": "your food",
        "sentence": "Makananmu dingin."
      }
    ],
    "relatedRootIds": ["id_suffix_nya"],
    "pronunciationIpa": "/mu/",
    "pronunciationVariants": [
      {
        "accent": "indonesian",
        "ipa": "mu"
      }
    ]
  },
  {
    "id": "id_suffix_lah",
    "root": "-lah",
    "type": "suffix",
    "languageOrigin": "Indonesian",
    "meaning": "imperative/emphatic particle",
    "examples": [
      {
        "word": "bacalah",
        "meaning": "read!",
        "sentence": "Bacalah buku itu!"
      },
      {
        "word": "tulislah",
        "meaning": "write!",
        "sentence": "Tulislah dengan benar!"
      },
      {
        "word": "makanlah",
        "meaning": "eat!",
        "sentence": "Makanlah yang banyak!"
      }
    ],
    "relatedRootIds": ["id_base_baca", "id_base_tulis", "id_base_makan"],
    "pronunciationIpa": "/lah/",
    "pronunciationVariants": [
      {
        "accent": "indonesian",
        "ipa": "lah"
      }
    ]
  },
  {
    "id": "id_suffix_pun",
    "root": "-pun",
    "type": "suffix",
    "languageOrigin": "Indonesian",
    "meaning": "even; also; any",
    "examples": [
      {
        "word": "siapapun",
        "meaning": "anyone",
        "sentence": "Siapapun boleh masuk."
      },
      {
        "word": "meskipun",
        "meaning": "although",
        "sentence": "Meskipun hujan, saya pergi."
      },
      {
        "word": "kapanpun",
        "meaning": "whenever",
        "sentence": "Kapanpun kamu siap, kita berangkat."
      }
    ],
    "relatedRootIds": [],
    "pronunciationIpa": "/pun/",
    "pronunciationVariants": [
      {
        "accent": "indonesian",
        "ipa": "pun"
      }
    ]
  },
  {
    "id": "id_suffix_kah",
    "root": "-kah",
    "type": "suffix",
    "languageOrigin": "Indonesian",
    "meaning": "question particle",
    "examples": [
      {
        "word": "apakah",
        "meaning": "whether; is it",
        "sentence": "Apakah dia sudah datang?"
      },
      {
        "word": "siapakah",
        "meaning": "who (question)",
        "sentence": "Siapakah orang itu?"
      },
      {
        "word": "mengapakah",
        "meaning": "why (formal)",
        "sentence": "Mengapakah kamu pergi?"
      }
    ],
    "relatedRootIds": [],
    "pronunciationIpa": "/kah/",
    "pronunciationVariants": [
      {
        "accent": "indonesian",
        "ipa": "kah"
      }
    ]
  },
  {
    "id": "id_suffix_wan",
    "root": "-wan",
    "type": "suffix",
    "languageOrigin": "Indonesian",
    "meaning": "person; specialist",
    "examples": [
      {
        "word": "ilmuwan",
        "meaning": "scientist",
        "sentence": "Ilmuwan itu menemukan vaksin."
      },
      {
        "word": "seniman",
        "meaning": "artist",
        "sentence": "Seniman itu terkenal."
      },
      {
        "word": "warga negara",
        "meaning": "citizen",
        "sentence": "Warga negara memiliki hak."
      }
    ],
    "relatedRootIds": [],
    "pronunciationIpa": "/wan/",
    "pronunciationVariants": [
      {
        "accent": "indonesian",
        "ipa": "wan"
      }
    ]
  },
  {
    "id": "id_suffix_wati",
    "root": "-wati",
    "type": "suffix",
    "languageOrigin": "Indonesian",
    "meaning": "female person; specialist",
    "examples": [
      {
        "word": "seniwati",
        "meaning": "female artist",
        "sentence": "Seniwati itu berbakat."
      },
      {
        "word": "ilmuwati",
        "meaning": "female scientist",
        "sentence": "Ilmuwati itu meneliti hutan."
      },
      {
        "word": "pahlawanwati",
        "meaning": "heroine",
        "sentence": "Pahlawanwati itu dihormati."
      }
    ],
    "relatedRootIds": ["id_suffix_wan"],
    "pronunciationIpa": "/wa.ti/",
    "pronunciationVariants": [
      {
        "accent": "indonesian",
        "ipa": "wati"
      }
    ]
  },
  {
    "id": "id_suffix_saja",
    "root": "-saja",
    "type": "suffix",
    "languageOrigin": "Indonesian",
    "meaning": "only; just",
    "examples": [
      {
        "word": "saya saja",
        "meaning": "just me",
        "sentence": "Yang datang saya saja."
      },
      {
        "word": "ini saja",
        "meaning": "only this",
        "sentence": "Beli ini saja."
      },
      {
        "word": "satu saja",
        "meaning": "only one",
        "sentence": "Satu saja cukup."
      }
    ],
    "relatedRootIds": ["id_suffix_pun"],
    "pronunciationIpa": "/sa.dʒa/",
    "pronunciationVariants": [
      {
        "accent": "indonesian",
        "ipa": "saja"
      }
    ]
  }
]
